{
  "appId": "com.semaplan.melomania",
  "productName": "Semaplan Melomania",
  "asar": true,
  "extraMetadata": {
    "main": "Aplicaciones/Desktop/Melomania/Main_Process.js"
  },
  "directories": {
    "output": "Aplicaciones/Desktop/Melomania/Dist_Melomania"
  },
  "files": [
    "Aplicaciones/Desktop/Melomania/**/*",
    "!Aplicaciones/Desktop/Melomania/Dist_Melomania{,/**/*}",
    "Aplicaciones/Desktop/Servidor_Local.js",
    "Aplicaciones/Desktop/Semaplan.ico",
    "package.json"
  ],
  "win": {
    "icon": "Aplicaciones/Desktop/Semaplan.ico",
    "signAndEditExecutable": false,
    "target": [
      "portable"
    ],
    "artifactName": "Semaplan-Melomania-${version}.${ext}"
  }
}
